audio_snippets/__init__.py
audio_snippets/_modidx.py
audio_snippets/_nbdev.py
audio_snippets/core.py
audio_snippets/fft.py
audio_snippets-0.0.1.dist-info/LICENSE
audio_snippets-0.0.1.dist-info/METADATA
audio_snippets-0.0.1.dist-info/WHEEL
audio_snippets-0.0.1.dist-info/entry_points.txt
audio_snippets-0.0.1.dist-info/top_level.txt
audio_snippets-0.0.1.dist-info/RECORD
