Metadata-Version: 2.1
Name: audio-snippets
Version: 0.0.1
Summary: Simple snippets for audio analysis
Home-page: https://github.com/sizhky/audio_snippets/tree/master/
Author: Yeshwanth
Author-email: 1992chinna@gmail.com
License: Apache Software License 2.0
Keywords: audio,snippets
Platform: UNKNOWN
Classifier: Development Status :: 3 - Alpha
Classifier: Intended Audience :: Developers
Classifier: Natural Language :: English
Classifier: Programming Language :: Python :: 3.6
Classifier: Programming Language :: Python :: 3.7
Classifier: Programming Language :: Python :: 3.8
Classifier: License :: OSI Approved :: Apache Software License
Requires-Python: >=3.6
License-File: LICENSE
Requires-Dist: pip
Requires-Dist: packaging
Requires-Dist: librosa
Requires-Dist: plotly
Requires-Dist: torch-snippets
Requires-Dist: soundfile
Provides-Extra: dev
